mcp_get_weather/__init__.py
mcp_get_weather/__main__.py
mcp_get_weather/server.py
huadongligongdapenghuhauhuau-0.1.0.dist-info/METADATA
huadongligongdapenghuhauhuau-0.1.0.dist-info/WHEEL
huadongligongdapenghuhauhuau-0.1.0.dist-info/entry_points.txt
huadongligongdapenghuhauhuau-0.1.0.dist-info/top_level.txt
huadongligongdapenghuhauhuau-0.1.0.dist-info/RECORD
