Metadata-Version: 2.4
Name: huadongligongdapenghuhauhuau
Version: 0.1.0
Summary: 输入OpenWeather-API-KEY，获取天气信息。
Requires-Python: >=3.10
Requires-Dist: httpx>=0.28.1
Requires-Dist: mcp>=1.9.4
Requires-Dist: openai>=1.75.0
Requires-Dist: python-dotenv>=1.1.0
Requires-Dist: setuptools>=80.9.0
